sshtunnelproxy/__init__.py
sshtunnelproxy/settings.py
sshtunnelproxy/sshtunnelproxy.py
sshtunnelproxy/management/__init__.py
sshtunnelproxy/management/commands/__init__.py
sshtunnelproxy/management/commands/opensshtunnelproxy.py
django_ssh_tunnel_proxy-1.0.4.dist-info/METADATA
django_ssh_tunnel_proxy-1.0.4.dist-info/WHEEL
django_ssh_tunnel_proxy-1.0.4.dist-info/licenses/LICENSE
django_ssh_tunnel_proxy-1.0.4.dist-info/RECORD
