Metadata-Version: 2.4
Name: django-ssh-tunnel-proxy
Version: 1.0.4
Summary: A Django plugin that allows ssh remote tunnels.
Project-URL: Homepage, https://github.com/SD-Software-Design-GmbH/django-ssh-tunnel-proxy
Project-URL: Issues, https://github.com/SD-Software-Design-GmbH/django-ssh-tunnel-proxy/issues
Author-email: Julian Bürklin <jb@software-design.de>
License-File: LICENSE
Classifier: License :: OSI Approved :: MIT License
Classifier: Operating System :: OS Independent
Classifier: Programming Language :: Python :: 3
Requires-Python: >=3.6
